Users/eysenck/.timetracker/config.toml
timetracker/__init__.py
timetracker/cli.py
timetracker/constants.py
timetracker/timetracker.py
timetracker/utils.py
timetracker_cli-1.3.0.dist-info/LICENSE
timetracker_cli-1.3.0.dist-info/METADATA
timetracker_cli-1.3.0.dist-info/WHEEL
timetracker_cli-1.3.0.dist-info/entry_points.txt
timetracker_cli-1.3.0.dist-info/top_level.txt
timetracker_cli-1.3.0.dist-info/RECORD
